molfeat/__init__.py
molfeat/_version.py
molfeat/viz.py
molfeat/calc/__init__.py
molfeat/calc/_atom_bond_features.py
molfeat/calc/_map4.py
molfeat/calc/_mhfp.py
molfeat/calc/_serializable_classes.py
molfeat/calc/atom.py
molfeat/calc/base.py
molfeat/calc/bond.py
molfeat/calc/cats.py
molfeat/calc/descriptors.py
molfeat/calc/fingerprints.py
molfeat/calc/pharmacophore.py
molfeat/calc/shape.py
molfeat/calc/skeys.py
molfeat/calc/tree.py
molfeat/data/__init__.py
molfeat/data/cats_features.fdef
molfeat/data/elements.xz
molfeat/data/elements_completed.xz
molfeat/data/origin.xz
molfeat/data/skey_parameters.csv
molfeat/plugins/__init__.py
molfeat/plugins/entry_point.py
molfeat/plugins/exception.py
molfeat/plugins/factories.py
molfeat/store/__init__.py
molfeat/store/loader.py
molfeat/store/modelcard.py
molfeat/store/modelstore.py
molfeat/trans/__init__.py
molfeat/trans/base.py
molfeat/trans/concat.py
molfeat/trans/fp.py
molfeat/trans/graph/__init__.py
molfeat/trans/graph/adj.py
molfeat/trans/graph/tree.py
molfeat/trans/pretrained/__init__.py
molfeat/trans/pretrained/base.py
molfeat/trans/pretrained/dgl_pretrained.py
molfeat/trans/pretrained/fcd.py
molfeat/trans/pretrained/graphormer.py
molfeat/trans/pretrained/hf_transformers.py
molfeat/trans/struct/__init__.py
molfeat/trans/struct/esm.py
molfeat/trans/struct/prot1D.py
molfeat/utils/__init__.py
molfeat/utils/cache.py
molfeat/utils/commons.py
molfeat/utils/const.py
molfeat/utils/converters.py
molfeat/utils/datatype.py
molfeat/utils/log.py
molfeat/utils/parsing.py
molfeat/utils/pooler.py
molfeat/utils/requires.py
molfeat/utils/state.py
molfeat-0.11.0.dist-info/licenses/LICENSE
molfeat-0.11.0.dist-info/METADATA
molfeat-0.11.0.dist-info/WHEEL
molfeat-0.11.0.dist-info/top_level.txt
molfeat-0.11.0.dist-info/RECORD
