Metadata-Version: 2.4
Name: molfeat
Version: 0.11.0
Summary: molfeat - the hub for all your molecular featurizers
Author-email: Emmanuel Noutahi <emmanuel.noutahi@hotmail.ca>
License: Apache
Project-URL: Website, https://molfeat.datamol.io
Project-URL: Source Code, https://github.com/datamol-io/molfeat
Project-URL: Bug Tracker, https://github.com/datamol-io/molfeat/issues
Project-URL: Documentation, https://molfeat-docs.datamol.io/
Classifier: Development Status :: 5 - Production/Stable
Classifier: Intended Audience :: Developers
Classifier: Intended Audience :: Healthcare Industry
Classifier: Intended Audience :: Science/Research
Classifier: Topic :: Scientific/Engineering :: Artificial Intelligence
Classifier: Topic :: Scientific/Engineering :: Bio-Informatics
Classifier: Topic :: Scientific/Engineering :: Information Analysis
Classifier: Topic :: Scientific/Engineering :: Medical Science Apps.
Classifier: Natural Language :: English
Classifier: Operating System :: OS Independent
Classifier: Programming Language :: Python
Classifier: Programming Language :: Python :: 3
Classifier: Programming Language :: Python :: 3.9
Classifier: Programming Language :: Python :: 3.10
Requires-Python: <3.11,>=3.9
License-File: LICENSE
Requires-Dist: tqdm
Requires-Dist: loguru
Requires-Dist: joblib
Requires-Dist: filelock
Requires-Dist: fsspec>=2021.9
Requires-Dist: s3fs>=2021.9
Requires-Dist: gcsfs>=2021.9
Requires-Dist: pandas
Requires-Dist: numpy
Requires-Dist: scipy
Requires-Dist: torch>=1.13
Requires-Dist: datamol>=0.8.0
Requires-Dist: pyyaml
Requires-Dist: platformdirs
Requires-Dist: matplotlib
Requires-Dist: h5py
Requires-Dist: pyarrow
Requires-Dist: pydantic>=2.0.0
Requires-Dist: platformdirs
Requires-Dist: scikit-learn
Requires-Dist: packaging
Requires-Dist: pmapper
Requires-Dist: mordredcommunity
Requires-Dist: python-dotenv
Requires-Dist: rdkit
Provides-Extra: dgl
Requires-Dist: dgl<=2.0.0,>=1.1.1; extra == "dgl"
Requires-Dist: dgllife>=0.3.2; extra == "dgl"
Provides-Extra: graphormer
Requires-Dist: graphormer-pretrained; extra == "graphormer"
Provides-Extra: transformer
Requires-Dist: tokenizers<0.13.2; extra == "transformer"
Requires-Dist: transformers; extra == "transformer"
Requires-Dist: sentencepiece; extra == "transformer"
Provides-Extra: fcd
Requires-Dist: fcd_torch; extra == "fcd"
Provides-Extra: viz
Requires-Dist: nglview; extra == "viz"
Requires-Dist: ipywidgets; extra == "viz"
Provides-Extra: pyg
Requires-Dist: torch_geometric>=2.4.0; extra == "pyg"
Provides-Extra: all
Requires-Dist: dgl; extra == "all"
Requires-Dist: dgllife; extra == "all"
Requires-Dist: graphormer-pretrained; extra == "all"
Requires-Dist: tokenizers<0.13.2; extra == "all"
Requires-Dist: transformers; extra == "all"
Requires-Dist: fcd_torch; extra == "all"
Requires-Dist: nglview; extra == "all"
Requires-Dist: ipywidgets; extra == "all"
Requires-Dist: torch_geometric>=2.4.0; extra == "all"
Provides-Extra: test
Requires-Dist: pytest>=6.0; extra == "test"
Requires-Dist: pytest-dotenv; extra == "test"
Requires-Dist: pytest-cov; extra == "test"
Requires-Dist: pytest-xdist; extra == "test"
Requires-Dist: black>=22; extra == "test"
Requires-Dist: ruff; extra == "test"
Provides-Extra: docs
Requires-Dist: mkdocs; extra == "docs"
Requires-Dist: mike; extra == "docs"
Requires-Dist: mdx_truly_sane_lists; extra == "docs"
Requires-Dist: mkdocs-material>=7.1.1; extra == "docs"
Requires-Dist: mkdocs-jupyter>=0.24.8; extra == "docs"
Requires-Dist: mkdocstrings; extra == "docs"
Requires-Dist: mkdocstrings-python; extra == "docs"
Requires-Dist: markdown-include; extra == "docs"
Provides-Extra: dev
Requires-Dist: molfeat[test]; extra == "dev"
Requires-Dist: molfeat[all]; extra == "dev"
Requires-Dist: molfeat[docs]; extra == "dev"
Requires-Dist: pre-commit; extra == "dev"
Dynamic: license-file
